digitall/__init__.py
digitall-0.0.1.dist-info/METADATA
digitall-0.0.1.dist-info/WHEEL
digitall-0.0.1.dist-info/top_level.txt
digitall-0.0.1.dist-info/RECORD
