Metadata-Version: 2.4
Name: digitall
Version: 0.0.1
Summary: we dig-it-all.
Author: justauth
License: MIT
Classifier: Programming Language :: Python :: 3
Classifier: License :: OSI Approved :: MIT License
Classifier: Operating System :: OS Independent
Requires-Python: >=3.6
Dynamic: author
Dynamic: classifier
Dynamic: description
Dynamic: description-content-type
Dynamic: license
Dynamic: requires-python
Dynamic: summary
